differential_evolution/__init__.py
differential_evolution/concurrent_eval.py
differential_evolution/differential_evolution.py
differential_evolution/evolution_strategy.py
differential_evolution/openmdao_driver.py
differential_evolution/version.py
differential_evolution-1.12.0.dist-info/LICENSE
differential_evolution-1.12.0.dist-info/METADATA
differential_evolution-1.12.0.dist-info/WHEEL
differential_evolution-1.12.0.dist-info/top_level.txt
differential_evolution-1.12.0.dist-info/RECORD
