Metadata-Version: 2.1
Name: differential-evolution
Version: 1.12.0
Summary: Differential Evolution Algorithm with OpenMDAO Driver
Home-page: https://github.com/daniel-de-vries/differential-evolution
Author: Daniel de Vries
Author-email: danieldevries6@gmail.com
License: MIT License
Download-URL: https://github.com/daniel-de-vries/differential-evolution/archive/v1.12.0.tar.gz
Keywords: optimization,black-box,data science,differential,evolution,evolutionary,algorithms
Platform: UNKNOWN
Classifier: Development Status :: 4 - Beta
Classifier: Intended Audience :: Developers
Classifier: Intended Audience :: Science/Research
Classifier: License :: OSI Approved :: MIT License
Classifier: Natural Language :: English
Classifier: Operating System :: POSIX :: Linux
Classifier: Operating System :: MacOS :: MacOS X
Classifier: Operating System :: Microsoft :: Windows
Classifier: Programming Language :: Python
Classifier: Programming Language :: Python :: 2.7
Classifier: Programming Language :: Python :: 3.7
Requires-Dist: numpy (>=1.17)
Requires-Dist: openmdao (<2.10,>=2.8)
Requires-Dist: tqdm (<5,>=4.32)
Requires-Dist: six (<1.13,>=1.12)
